{
    "id": "116096",
    "displayId": "116096",
    "version": "",
    "texture": "https://esoicons.uesp.net/esoui/art/icons/ability_artifact_volendrung_006.png",
    "name": "Ruinous Cyclone",
    "description": "Turn into a living cyclone, dealing 7875 Physical Damage every 0.5 seconds for 7 seconds in an 8m radius, while pulling all enemies within 15m closer to you.",
    "descHeader": "",
    "duration": "7000",
    "startTime": "500",
    "tickTime": "500",
    "cooldown": "0",
    "cost": "-1",
    "target": "Self",
    "minRange": "0",
    "maxRange": "0",
    "radius": "0",
    "isPassive": "0",
    "isChanneled": "1",
    "isPermanent": "0",
    "isPlayer": "1",
    "rank": "4",
    "morph": "0",
    "learnedLevel": "1",
    "castTime": "0",
    "channelTime": "7500",
    "angleDistance": "0",
    "mechanic": "Adrenaline",
    "buffType": "",
    "isToggle": "0",
    "chargeFreq": "0",
    "skillIndex": "1",
    "skillType": "Alliance War",
    "skillLine": "Volendrung",
    "raceType": "",
    "classType": "",
    "setName": "",
    "baseAbilityId": "116096",
    "prevSkill": "-1",
    "nextSkill": "-1",
    "nextSkill2": "-1",
    "upgradeLines": "",
    "effectLines": "",
    "numCoefVars": "-1",
    "coefDescription": "",
    "type1": "Invalid",
    "a1": "-1",
    "b1": "-1",
    "c1": "-1",
    "R1": "-1",
    "avg1": "-1",
    "type2": "Invalid",
    "a2": "-1",
    "b2": "-1",
    "c2": "-1",
    "R2": "-1",
    "avg2": "-1",
    "type3": "Invalid",
    "a3": "-1",
    "b3": "-1",
    "c3": "-1",
    "R3": "-1",
    "avg3": "-1",
    "type4": "Invalid",
    "a4": "-1",
    "b4": "-1",
    "c4": "-1",
    "R4": "-1",
    "avg4": "-1",
    "type5": "Invalid",
    "a5": "-1",
    "b5": "-1",
    "c5": "-1",
    "R5": "-1",
    "avg5": "-1",
    "type6": "Invalid",
    "a6": "-1",
    "b6": "-1",
    "c6": "-1",
    "R6": "-1",
    "avg6": "-1",
    "rawDescription": "Turn into a living cyclone, dealing <<1>> every <<2>> for 7 seconds in an 8m radius, while pulling all enemies within 15m closer to you.",
    "rawTooltip": "",
    "rawCoef": "",
    "coefTypes": "",
    "buffs": [],
    "debuffs": []
}