{
    "id": "63335",
    "displayId": "61536",
    "version": "",
    "texture": "https://esoicons.uesp.net/esoui/art/icons/ability_ava_mystic_guard.png",
    "name": "Mystic Guard",
    "description": "Create a lifebond between you and an allied player. While bonded, 30% of the damage they take is instead redistributed to you.  You and your bonded ally also gain Minor Vitality, increasing your healing received by 8%.  The bond will remain until you recast the spell or move more than 15 meters away from your ally.",
    "descHeader": "",
    "duration": "0",
    "startTime": "0",
    "tickTime": "500",
    "cooldown": "0",
    "cost": "3132",
    "target": "",
    "minRange": "0",
    "maxRange": "1500",
    "radius": "0",
    "isPassive": "0",
    "isChanneled": "0",
    "isPermanent": "0",
    "isPlayer": "1",
    "rank": "4",
    "morph": "1",
    "learnedLevel": "5",
    "castTime": "0",
    "channelTime": "0",
    "angleDistance": "0",
    "mechanic": "Stamina",
    "buffType": "",
    "isToggle": "0",
    "chargeFreq": "0",
    "skillIndex": "4",
    "skillType": "Alliance War",
    "skillLine": "Support",
    "raceType": "",
    "classType": "",
    "setName": "",
    "baseAbilityId": "61511",
    "prevSkill": "63329",
    "nextSkill": "0",
    "nextSkill2": "0",
    "upgradeLines": "",
    "effectLines": "You and your bonded ally also gain Minor Vitality, increasing your healing received.",
    "numCoefVars": "-1",
    "coefDescription": "",
    "type1": "Invalid",
    "a1": "-1",
    "b1": "-1",
    "c1": "-1",
    "R1": "-1",
    "avg1": "-1",
    "type2": "Invalid",
    "a2": "-1",
    "b2": "-1",
    "c2": "-1",
    "R2": "-1",
    "avg2": "-1",
    "type3": "Invalid",
    "a3": "-1",
    "b3": "-1",
    "c3": "-1",
    "R3": "-1",
    "avg3": "-1",
    "type4": "Invalid",
    "a4": "-1",
    "b4": "-1",
    "c4": "-1",
    "R4": "-1",
    "avg4": "-1",
    "type5": "Invalid",
    "a5": "-1",
    "b5": "-1",
    "c5": "-1",
    "R5": "-1",
    "avg5": "-1",
    "type6": "Invalid",
    "a6": "-1",
    "b6": "-1",
    "c6": "-1",
    "R6": "-1",
    "avg6": "-1",
    "rawDescription": "Create a lifebond between you and an allied player. While bonded, |cffffff30|r% of the damage they take is instead redistributed to you.\n\nYou and your bonded ally also gain Minor Vitality, increasing your healing received by <<1>>.\n\nThe bond will remain until you recast the spell or move more than |cffffff15|r meters away from your ally.",
    "rawTooltip": "",
    "rawCoef": "",
    "coefTypes": "",
    "buffs": [],
    "debuffs": []
}