{
    "id": "43067",
    "displayId": "40328",
    "version": "",
    "texture": "https://esoicons.uesp.net/esoui/art/icons/ability_otherclass_001_a.png",
    "name": "Soul Splitting Trap",
    "description": "Lay claim to enemy souls, dealing 2316 Magic Damage to your target and any other nearby enemies over 10 seconds.  Fills an empty Soul Gem if an affected enemy dies.",
    "descHeader": "",
    "duration": "10000",
    "startTime": "0",
    "tickTime": "0",
    "cooldown": "0",
    "cost": "2430",
    "target": "Enemy",
    "minRange": "0",
    "maxRange": "2800",
    "radius": "800",
    "isPassive": "0",
    "isChanneled": "0",
    "isPermanent": "0",
    "isPlayer": "1",
    "rank": "4",
    "morph": "1",
    "learnedLevel": "1",
    "castTime": "0",
    "channelTime": "0",
    "angleDistance": "0",
    "mechanic": "Magicka",
    "buffType": "",
    "isToggle": "0",
    "chargeFreq": "0",
    "skillIndex": "2",
    "skillType": "World",
    "skillLine": "Soul Magic",
    "raceType": "",
    "classType": "",
    "setName": "",
    "baseAbilityId": "26768",
    "prevSkill": "43063",
    "nextSkill": "0",
    "nextSkill2": "0",
    "upgradeLines": "",
    "effectLines": "Affects additional enemies near your initial target, but for less total damage.  Reduces the cost as the ability ranks up.",
    "numCoefVars": "1",
    "coefDescription": "Lay claim to enemy souls, dealing $1 Magic Damage to your target and any other nearby enemies over 10 seconds.  Fills an empty Soul Gem if an affected enemy dies.",
    "type1": "Ultimate",
    "a1": "0.103142",
    "b1": "1.0873",
    "c1": "-7.80284",
    "R1": "0.999994",
    "avg1": "2973.27",
    "type2": "Invalid",
    "a2": "-1",
    "b2": "-1",
    "c2": "-1",
    "R2": "-1",
    "avg2": "-1",
    "type3": "Invalid",
    "a3": "-1",
    "b3": "-1",
    "c3": "-1",
    "R3": "-1",
    "avg3": "-1",
    "type4": "Invalid",
    "a4": "-1",
    "b4": "-1",
    "c4": "-1",
    "R4": "-1",
    "avg4": "-1",
    "type5": "Invalid",
    "a5": "-1",
    "b5": "-1",
    "c5": "-1",
    "R5": "-1",
    "avg5": "-1",
    "type6": "Invalid",
    "a6": "-1",
    "b6": "-1",
    "c6": "-1",
    "R6": "-1",
    "avg6": "-1",
    "rawDescription": "Lay claim to enemy souls, dealing <<1>> to your target and any other nearby enemies over <<2>>.\n\nFills an empty Soul Gem if an affected enemy dies.",
    "rawTooltip": "",
    "rawCoef": "",
    "coefTypes": "",
    "buffs": [],
    "debuffs": [],
    "type_of_damage_1": "magic damage",
    "tick_1": 0,
    "duration_1": 10000,
    "after_1": 0,
    "synergy_1": false,
    "sloteable_1": false,
    "a1_scaled": 0.010314199999999999,
    "b1_scaled": 0.10873,
    "c1_scaled": -0.780284
}