{
    "id": "24320",
    "displayId": "21758",
    "version": "",
    "texture": "https://esoicons.uesp.net/esoui/art/icons/ability_templar_solar_disturbance.png",
    "name": "Solar Disturbance",
    "description": "Call down a fragment of the sun, dealing 1161 Magic Damage every 1 second for 8 seconds to enemies in the area and applying Major Maim to them for 10 seconds, reducing their damage done by 10%.  An ally near the fragment can activate the Supernova synergy, dealing 2607 Magic Damage to all enemies in the area and stunning them for 3 seconds.",
    "descHeader": "",
    "duration": "8000",
    "startTime": "0",
    "tickTime": "0",
    "cooldown": "0",
    "cost": "225",
    "target": "Ground",
    "minRange": "0",
    "maxRange": "2800",
    "radius": "800",
    "isPassive": "0",
    "isChanneled": "0",
    "isPermanent": "0",
    "isPlayer": "1",
    "rank": "4",
    "morph": "2",
    "learnedLevel": "12",
    "castTime": "0",
    "channelTime": "0",
    "angleDistance": "0",
    "mechanic": "Ultimate",
    "buffType": "",
    "isToggle": "0",
    "chargeFreq": "0",
    "skillIndex": "1",
    "skillType": "Class",
    "skillLine": "Dawn's Wrath",
    "raceType": "",
    "classType": "Templar",
    "setName": "",
    "baseAbilityId": "21752",
    "prevSkill": "24314",
    "nextSkill": "0",
    "nextSkill2": "0",
    "upgradeLines": "",
    "effectLines": "Reduces the cost and Major Maim stays on enemies after leaving the area.",
    "numCoefVars": "2",
    "coefDescription": "Call down a fragment of the sun, dealing $1 Magic Damage every 1 second for 8 seconds to enemies in the area and applying Major Maim to them for 10 seconds, reducing their damage done by 10%.  An ally near the fragment can activate the Supernova synergy, dealing $2 Magic Damage to all enemies in the area and stunning them for 3 seconds.",
    "type1": "Ultimate",
    "a1": "0.0516095",
    "b1": "0.542493",
    "c1": "-0.721718",
    "R1": "0.999999",
    "avg1": "1489.09",
    "type2": "Ultimate",
    "a2": "0.115996",
    "b2": "1.21655",
    "c2": "-1.464",
    "R2": "1",
    "avg2": "3342.95",
    "type3": "Invalid",
    "a3": "-1",
    "b3": "-1",
    "c3": "-1",
    "R3": "-1",
    "avg3": "-1",
    "type4": "Invalid",
    "a4": "-1",
    "b4": "-1",
    "c4": "-1",
    "R4": "-1",
    "avg4": "-1",
    "type5": "Invalid",
    "a5": "-1",
    "b5": "-1",
    "c5": "-1",
    "R5": "-1",
    "avg5": "-1",
    "type6": "Invalid",
    "a6": "-1",
    "b6": "-1",
    "c6": "-1",
    "R6": "-1",
    "avg6": "-1",
    "rawDescription": "Call down a fragment of the sun, dealing <<1>> every <<2>> for <<3>> to enemies in the area and applying Major Maim to them for <<4>>, reducing their damage done by <<5>>.\n\nAn ally near the fragment can activate the <<6>> synergy, dealing <<7>> to all enemies in the area and stunning them for <<8>>.",
    "rawTooltip": "",
    "rawCoef": "",
    "coefTypes": "",
    "buffs": [],
    "debuffs": [],
    "type_of_damage_1": "magic damage",
    "tick_1": 1000,
    "duration_1": 8000,
    "after_1": 0,
    "synergy_1": false,
    "sloteable_1": false,
    "a1_scaled": 0.0516095,
    "b1_scaled": 0.542493,
    "c1_scaled": -0.721718,
    "type_of_damage_2": "magic damage",
    "tick_2": 0,
    "duration_2": 3000,
    "after_2": 0,
    "synergy_2": false,
    "sloteable_2": false,
    "a2_scaled": 0.115996,
    "b2_scaled": 1.21655,
    "c2_scaled": -1.464
}